lumi_cua_sdk/__about__.py
lumi_cua_sdk/__init__.py
lumi_cua_sdk/config.py
lumi_cua_sdk/cua_client.py
lumi_cua_sdk/sandbox_client.py
lumi_cua_sdk/common/__init__.py
lumi_cua_sdk/common/socket_client.py
lumi_cua_sdk/models/__init__.py
lumi_cua_sdk/models/agent_planner_models.py
lumi_cua_sdk/models/common_models.py
lumi_cua_sdk/models/tool_server_models.py
lumi_cua_sdk/services/__init__.py
lumi_cua_sdk/services/agent_planner.py
lumi_cua_sdk/services/sandbox_manager.py
lumi_cua_sdk/services/sandbox_tool_server.py
lumi_cua_sdk-1.2.0.dist-info/METADATA
lumi_cua_sdk-1.2.0.dist-info/WHEEL
lumi_cua_sdk-1.2.0.dist-info/licenses/LICENSE
lumi_cua_sdk-1.2.0.dist-info/RECORD
