Metadata-Version: 2.4
Name: lumi_cua_sdk
Version: 1.2.0
Summary: This is the Python SDK for Computer Use Agent, allowing you to easily control the computer desktop environment from your applications.
Project-URL: Source, https://github.com/lelili2021/lumi-cua-sdk.git
Author-email: lvguojun <lvguojun.001@bytedance.com>, lelili <lelili@bytedance.com>
License-Expression: MIT
License-File: LICENSE
Classifier: Development Status :: 4 - Beta
Classifier: Programming Language :: Python
Classifier: Programming Language :: Python :: 3.12
Classifier: Programming Language :: Python :: Implementation :: CPython
Classifier: Programming Language :: Python :: Implementation :: PyPy
Requires-Python: >=3.12
Requires-Dist: aiohttp>=3.10.11
Requires-Dist: httpx
Requires-Dist: pydantic>=1.8.0
Requires-Dist: requests>=2.25.0
Requires-Dist: websockets>=10.0
